fs_ossfs/__init__.py
fs_ossfs/opener.py
fs_ossfs/ossfs.py
fs_ossfs/version.py
fs_ossfs-1.1.1.dist-info/LICENSE
fs_ossfs-1.1.1.dist-info/METADATA
fs_ossfs-1.1.1.dist-info/WHEEL
fs_ossfs-1.1.1.dist-info/entry_points.txt
fs_ossfs-1.1.1.dist-info/top_level.txt
fs_ossfs-1.1.1.dist-info/RECORD
