Metadata-Version: 2.1
Name: fs-ossfs
Version: 1.1.1
Summary: AliCloud OSS filesystem for PyFilesystem2
Home-page: https://github.com/go-choppy/fs.ossfs
Author: Jingcheng Yang
Author-email: yjcyxky@163.com
License: MIT
Keywords: pyfilesystem,AliCloud,oss
Platform: any
Classifier: Development Status :: 4 - Beta
Classifier: Intended Audience :: Developers
Classifier: License :: OSI Approved :: MIT License
Classifier: Operating System :: OS Independent
Classifier: Programming Language :: Python
Classifier: Programming Language :: Python :: 2.7
Classifier: Programming Language :: Python :: 3.3
Classifier: Programming Language :: Python :: 3.4
Classifier: Programming Language :: Python :: 3.5
Classifier: Programming Language :: Python :: 3.6
Classifier: Programming Language :: Python :: 3.7
Classifier: Topic :: System :: Filesystems
Requires-Dist: boto3 (~=1.7)
Requires-Dist: awscli (~=1.16.144)
Requires-Dist: fs (~=2.2)
Requires-Dist: six (~=1.10)
